django_mako/__init__.py
django_mako/__version__.py
django_mako/apps/__init__.py
django_mako/apps/django_mako_config.py
django_mako/py.typed
django_mako/template/__init__.py
django_mako/template/backend/__init__.py
django_mako/template/backend/debugging/__init__.py
django_mako/template/backend/debugging/mako_exception_info.py
django_mako/template/backend/engine/__init__.py
django_mako/template/backend/engine/mako_engine.py
django_mako/template/backend/exception/__init__.py
django_mako/template/backend/exception/lookup_exception_types.py
django_mako/template/backend/exception/mako_exception_handler.py
django_mako/template/backend/exception/positional_exception_types.py
django_mako/template/context_processors/__init__.py
django_mako/template/context_processors/_url.py
django_mako/template/mako_template_origin.py
django_mako/template/mako_template_wrapper.py
mako_for_django-1.0.0.dist-info/WHEEL
mako_for_django-1.0.0.dist-info/METADATA
mako_for_django-1.0.0.dist-info/RECORD
