Metadata-Version: 2.3
Name: mako-for-django
Version: 1.0.0
Summary: Mako template engine for Django.
Author: Ertuğrul Keremoğlu
Author-email: Ertuğrul Keremoğlu <ertugkeremoglu@gmail.com>
Classifier: Development Status :: 5 - Production/Stable
Classifier: Environment :: Plugins
Classifier: Environment :: Web Environment
Classifier: Framework :: Django
Classifier: Intended Audience :: Developers
Classifier: License :: OSI Approved :: MIT License
Classifier: Natural Language :: English
Classifier: Operating System :: OS Independent
Classifier: Programming Language :: Python
Classifier: Programming Language :: Python :: 3
Classifier: Topic :: Internet :: WWW/HTTP :: Dynamic Content
Classifier: Topic :: Software Development :: Libraries
Classifier: Topic :: Software Development :: User Interfaces
Classifier: Topic :: Text Processing :: Markup :: HTML
Classifier: Topic :: Utilities
Classifier: Typing :: Typed
Requires-Dist: mako-for-django[mako]
Requires-Dist: django>=5.2.5 ; extra == 'django'
Requires-Dist: mako>=1.3.10 ; extra == 'mako'
Requires-Dist: django-stubs[compatible-mypy]>=5.2.2 ; extra == 'mypy'
Requires-Dist: mypy>=1.17.1 ; extra == 'mypy'
Requires-Dist: ruff>=0.12.9 ; extra == 'ruff'
Requires-Python: >=3.13
Project-URL: Homepage, https://github.com/ertgl/mako-for-django
Project-URL: Issues, https://github.com/ertgl/mako-for-django/issues
Provides-Extra: django
Provides-Extra: mako
Provides-Extra: mypy
Provides-Extra: ruff
